{
    "defaultControl": {
        "fontColor": "#f0feff",
        "backgroundColor": "#42a3e7",
        "hoverBackgroundColor": "#7dc6e9",
        "focusBackgroundColor": "#7dc6e9",
        "activeBackgroundColor": "#3c95d1",
        "focusBorderColor": "#42a3e7",
    },

    "transparentButton": {
        "backgroundColor": "#00000100",
        "hoverBackgroundColor": "#60606060",
        "focusBackgroundColor": "#60606080",
        "activeBackgroundColor": "#40404080",
        "textShadow": {
            "color": "#a0acad",
            "offset": {
                "x": 1,
                "y": 1
            }
        },
    },

   "dynamicPanel": {
       "backgroundColor": "#23304300",
       "focusBackgroundColor": "#00a07e",
   },

    "staticPanel": {
        "a": "#425169",
        "b": "#38465f",
        "backgroundGradient": "24deg, #425169, #38465f"
    },

    "primaryFontColor": "#F0F0F0",
    "secondaryFontColor": "#CCCCCC",
    "noBackgroundInHierarchyTextShadow": {
        "color": "#a0a0a0",
        "offset": {
            "x": 1,
            "y": 1
        }
    },

    "staticBackground": {
        "impagePath": "backgrounds/black-10percent.png",
        "imageScaleMode": "StretchToFill"
    },
    
    "dynamicBackground": {
        "gradientRampFile": "gradients/ocean.png",
        "gradientType": "Linear",
        "gradientScale": 1.4,
        "gradientSmoothness": 0.8,
        "gradientAngle": 100,
        "gradientAnimation": true,
        "gradientAnimSpeed": 1.0,
        "gradientAnimAmplitude": 0.5,
        "particleFile": "particles/bubble.png",
        "particleOpacity": 0.3
    }
}